hashcache/__init__.py
hashcache/hashcache.py
hashcache/pickle_substitute_handlers.py
hashcache/utils.py
hashcache-0.1.0.dist-info/METADATA
hashcache-0.1.0.dist-info/WHEEL
hashcache-0.1.0.dist-info/top_level.txt
hashcache-0.1.0.dist-info/RECORD
