Metadata-Version: 2.4
Name: hashcache
Version: 0.1.0
Summary: Simple disk-based function result caching using Python decorators
Author-email: Daniel Samuelson <daniel.samuelson8@gmail.com>
License: MIT
Project-URL: Homepage, https://github.com/dansam8/hashcache
Project-URL: Repository, https://github.com/dansam8/hashcache
Project-URL: Issues, https://github.com/dansam8/hashcache/issues
Requires-Python: >=3.8
Provides-Extra: dill
Requires-Dist: dill; extra == "dill"
